naivenlp/__init__.py
naivenlp/correctors/__init__.py
naivenlp/correctors/abstract_corrector.py
naivenlp/correctors/deep_corrector.py
naivenlp/correctors/deep_corrector_test.py
naivenlp/correctors/kenlm_corrector.py
naivenlp/correctors/kenlm_corrector_test.py
naivenlp/datasource/__init__.py
naivenlp/datasource/sogou.py
naivenlp/datasource/sogou_test.py
naivenlp/similarity/__init__.py
naivenlp/structures/__init__.py
naivenlp/structures/trie.py
naivenlp/structures/trie_test.py
naivenlp/tokenizers/__init__.py
naivenlp/tokenizers/abstract_tokenizer.py
naivenlp/tokenizers/bert_tokenizer.py
naivenlp/tokenizers/bert_tokenizer_test.py
naivenlp/tokenizers/jieba_tokenizer.py
naivenlp/tokenizers/jieba_tokenizer_test.py
naivenlp/tokenizers/tokenizer.py
naivenlp/tokenizers/transformer_tokenizer.py
naivenlp/tokenizers/transformer_tokenizer_test.py
naivenlp/utils/__init__.py
naivenlp/utils/get_file.py
naivenlp/utils/texts.py
naivenlp-0.0.9.dist-info/LICENSE
naivenlp-0.0.9.dist-info/METADATA
naivenlp-0.0.9.dist-info/WHEEL
naivenlp-0.0.9.dist-info/top_level.txt
naivenlp-0.0.9.dist-info/RECORD
