Metadata-Version: 2.1
Name: naivenlp
Version: 0.0.9
Summary: NLP toolkit, including tokenization, sequence tagging, etc.
Home-page: https://github.com/luozhouyang/naivenlp
Author: ZhouYang Luo
Author-email: zhouyang.luo@gmail.com
License: Apache Software License
Platform: UNKNOWN
Classifier: Programming Language :: Python :: 3
Classifier: Programming Language :: Python :: 3.6
Classifier: Programming Language :: Python :: 3.7
Classifier: License :: OSI Approved :: Apache Software License
Classifier: Operating System :: OS Independent
Classifier: Topic :: Scientific/Engineering :: Artificial Intelligence
Requires-Dist: jieba
Requires-Dist: numpy
Requires-Dist: strsimpy
Requires-Dist: fake-useragent
Requires-Dist: requests
Provides-Extra: tf
Requires-Dist: tensorflow (>=2.2.0) ; extra == 'tf'
